Workbook
Name ConsultaIQY__49: TIIE!$A$1:$D$5226
Name ConsultaIQY__50: Balanza!$A$1:$C$421
Name ConsultaIQY__63: INPC!$A$1:$E$433
Name ConsultaIQY__70: TC!$A$1:$F$433
Name Indicadores20260820130130: desempleo!$A$1:$C$273

Sheet INPC
A1: Banco de México
A3: Índices de Precios al Consumidor y UDIS
A4: Principales índices mensuales
A6: Fecha de consulta: 24/08/2026 12:13:25
A8: Aviso importante: Algunas de las series que está consultando registra un cambio, por favor consulte los metadatos de las mismas.
A10: Título | B10: IPC Por objeto del gasto Nacional, I n d i c e G e n e r a l
A11: Periodo disponible | B11: Ene 1969 - Jul 2026
A12: Periodicidad | B12: Mensual
A13: Cifra | B13: Indices
A14: Unidad | B14: Sin Unidad
A15: Base | B15: 2Q Jul 2018
A16: Aviso | B16: Acorde con la Ley del Sistema Nacional de Información Estadística y Geográfica, publicada en el Diario Oficial de la Federación el 16 de abril de 2008, a partir del 15 de julio de 2011 el Instituto Nacional de Estadística y Geografía (INEGI) tiene la facultad exclusiva de elaborar y publicar los índices nacionales de precios. En consideración a lo anterior, la información sobre la inflación referente a junio de 2011 fue la última publicada por el Banco de México. El INEGI comenzó la difusión de la información con los resultados correspondientes a la primera quincena de julio de 2011.
A17: Tipo de información | B17: Índices
A18: Fecha | B18: SP1
A19: 33604 | B19: 11.657778
A20: 33635 | B20: 11.7959
A21: 33664 | B21: 11.915948
A22: 33695 | B22: 12.022171
A23: 33725 | B23: 12.101438
A24: 33756 | B24: 12.183345
A25: 33786 | B25: 12.260272
A26: 33817 | B26: 12.335592
A27: 33848 | B27: 12.442897
A28: 33878 | B28: 12.532494
A29: 33909 | B29: 12.63662
A30: 33939 | B30: 12.816553
... A433: 46204 | B433: 145.169

Sheet PIB
A1: Instituto Nacional de Estadística y Geografía (INEGI)
A2: Banco de Información Económica (BIE)
A3: Fecha de consulta: 21/09/2026 11:58:10
A5: Millones de pesos a precios de 2018
A6: Periodos | B6: Área geográfica | C6: Indicadores económicos de coyuntura > Producto interno bruto trimestral, base 2018 > Series desestacionalizadas y tendencia-ciclo > A precios de 2018 > Total > Serie desestacionalizada > Valores absolutos (Millones de pesos a precios de 2018) Trimestral /f1 /p1
A7: 1993/01 p1 | B7: 00 Estados Unidos Mexicanos | C7: 13804634
A8: 1993/02 p1 | B8: 00 Estados Unidos Mexicanos | C8: 13803749
A9: 1993/03 p1 | B9: 00 Estados Unidos Mexicanos | C9: 13964070
A10: 1993/04 p1 | B10: 00 Estados Unidos Mexicanos | C10: 14051913
A11: 1994/01 p1 | B11: 00 Estados Unidos Mexicanos | C11: 14194172
A12: 1994/02 p1 | B12: 00 Estados Unidos Mexicanos | C12: 14517686
A13: 1994/03 p1 | B13: 00 Estados Unidos Mexicanos | C13: 14596218
A14: 1994/04 p1 | B14: 00 Estados Unidos Mexicanos | C14: 14753231
A15: 1995/01 p1 | B15: 00 Estados Unidos Mexicanos | C15: 14081579
A16: 1995/02 p1 | B16: 00 Estados Unidos Mexicanos | C16: 13224738
A17: 1995/03 p1 | B17: 00 Estados Unidos Mexicanos | C17: 13508532
A18: 1995/04 p1 | B18: 00 Estados Unidos Mexicanos | C18: 13817356
... A140: 2026/02 p1 | B140: 00 Estados Unidos Mexicanos | C140: 25971193
A142: Notas y Llamadas:
A143: /p1 Preliminar
A145: Fuente:
A146: /f1 INEGI. Series calculadas por métodos econométricos a partir de las series originales del Producto Interno Bruto trimestral

Sheet Consumo
A1: Fecha | B1: IMCP | C1: ANTAD | D1: AUTOS | E1: TARJETAS
A2: 33970 | B2: ='[1]IQY IMCP'!O7 -> 52.534749 | C2: =[1]OMSPT2!F51 -> 41.229636 | D2: =[1]Cálculos!J3 -> 43.885652
A3: 34001 | B3: ='[1]IQY IMCP'!O8 -> 53.222631 | C3: =[1]OMSPT2!F52 -> 42.193635 | D3: =[1]Cálculos!J4 -> 46.534328
A4: 34029 | B4: ='[1]IQY IMCP'!O9 -> 53.786784 | C4: =[1]OMSPT2!F53 -> 42.432923 | D4: =[1]Cálculos!J5 -> 46.419105
A5: 34060 | B5: ='[1]IQY IMCP'!O10 -> 53.186943 | C5: =[1]OMSPT2!F54 -> 43.442106 | D5: =[1]Cálculos!J6 -> 40.280903
A6: 34090 | B6: ='[1]IQY IMCP'!O11 -> 53.997282 | C6: =[1]OMSPT2!F55 -> 43.715282 | D6: =[1]Cálculos!J7 -> 42.999499
A7: 34121 | B7: ='[1]IQY IMCP'!O12 -> 53.561451 | C7: =[1]OMSPT2!F56 -> 43.871378 | D7: =[1]Cálculos!J8 -> 42.022632
A8: 34151 | B8: ='[1]IQY IMCP'!O13 -> 53.502469 | C8: =[1]OMSPT2!F57 -> 44.633198 | D8: =[1]Cálculos!J9 -> 41.125108
A9: 34182 | B9: ='[1]IQY IMCP'!O14 -> 53.25086 | C9: =[1]OMSPT2!F58 -> 44.745627 | D9: =[1]Cálculos!J10 -> 39.532712
A10: 34213 | B10: ='[1]IQY IMCP'!O15 -> 53.711089 | C10: =[1]OMSPT2!F59 -> 43.48472 | D10: =[1]Cálculos!J11 -> 37.521818
A11: 34243 | B11: ='[1]IQY IMCP'!O16 -> 53.785837 | C11: =[1]OMSPT2!F60 -> 44.706156 | D11: =[1]Cálculos!J12 -> 34.522695
A12: 34274 | B12: ='[1]IQY IMCP'!O17 -> 53.531021 | C12: =[1]OMSPT2!F61 -> 44.778227 | D12: =[1]Cálculos!J13 -> 35.39666
A13: 34304 | B13: ='[1]IQY IMCP'!O18 -> 56.050041 | C13: =[1]OMSPT2!F62 -> 45.492926 | D13: =[1]Cálculos!J14 -> 34.066839
... A193: 39783 | B193: ='[1]IQY IMCP'!O198 -> 80.643357 | C193: =[1]OMSPT2!F242 -> 89.709954 | D193: =[1]Cálculos!J194 -> 59.319462
A194: 39814 | B194: ='[1]IQY IMCP'!O199 -> 78.419706 | C194: =[1]OMSPT2!F243 -> 94.921049 | D194: =[1]Cálculos!J195 -> 57.631929 | E194: =[1]MARURI!CO6 -> 33.101005
A195: 39845 | B195: ='[1]IQY IMCP'!O200 -> 78.524042 | C195: =[1]OMSPT2!F244 -> 95.348679 | D195: =[1]Cálculos!J196 -> 56.400145 | E195: =[1]MARURI!CO7 -> 33.393455
A196: 39873 | B196: ='[1]IQY IMCP'!O201 -> 78.639785 | C196: =[1]OMSPT2!F245 -> 95.697314 | D196: =[1]Cálculos!J197 -> 53.967732 | E196: =[1]MARURI!CO8 -> 33.393371
A197: 39904 | B197: ='[1]IQY IMCP'!O202 -> 78.22568 | C197: =[1]OMSPT2!F246 -> 95.758736 | D197: =[1]Cálculos!J198 -> 50.788903 | E197: =[1]MARURI!CO9 -> 34.004989
A198: 39934 | B198: ='[1]IQY IMCP'!O203 -> 75.490082 | C198: =[1]OMSPT2!F247 -> 94.385518 | D198: =[1]Cálculos!J199 -> 48.099937 | E198: =[1]MARURI!CO10 -> 32.502174
A199: 39965 | B199: ='[1]IQY IMCP'!O204 -> 77.964014 | C199: =[1]OMSPT2!F248 -> 94.50878 | D199: =[1]Cálculos!J200 -> 51.308858 | E199: =[1]MARURI!CO11 -> 34.307894
A200: 39995 | B200: ='[1]IQY IMCP'!O205 -> 78.925041 | C200: =[1]OMSPT2!F249 -> 95.383333 | D200: =[1]Cálculos!J201 -> 50.369765 | E200: =[1]MARURI!CO12 -> 34.777508
A201: 40026 | B201: ='[1]IQY IMCP'!O206 -> 79.72018 | C201: =[1]OMSPT2!F250 -> 96.737508 | D201: =[1]Cálculos!J202 -> 51.246157 | E201: =[1]MARURI!CO13 -> 34.628867
A202: 40057 | B202: ='[1]IQY IMCP'!O207 -> 79.475158 | C202: =[1]OMSPT2!F251 -> 95.661571 | D202: =[1]Cálculos!J203 -> 50.801211 | E202: =[1]MARURI!CO14 -> 35.062635
A203: 40087 | B203: ='[1]IQY IMCP'!O208 -> 80.322077 | C203: =[1]OMSPT2!F252 -> 95.647095 | D203: =[1]Cálculos!J204 -> 53.602602 | E203: =[1]MARURI!CO15 -> 35.488936
A204: 40118 | B204: ='[1]IQY IMCP'!O209 -> 81.182635 | C204: =[1]OMSPT2!F253 -> 94.334142 | D204: =[1]Cálculos!J205 -> 52.81186 | E204: =[1]MARURI!CO16 -> 35.490169
A205: 40148 | B205: ='[1]IQY IMCP'!O210 -> 81.694163 | C205: =[1]OMSPT2!F254 -> 97.309728 | D205: =[1]Cálculos!J206 -> 53.584837 | E205: =[1]MARURI!CO17 -> 34.932891
... A402: 46143 | B402: ='[1]IQY IMCP'!O407 -> 113.96456 | C402: =[1]OMSPT2!F451 -> 175.98201 | D402: =[1]Cálculos!J403 -> 110.32947 | E402: =[1]MARURI!CO214 -> 218.63377
A403: 46174 | C403: =[1]OMSPT2!F452 -> 175.27413 | D403: =[1]Cálculos!J404 -> 109.07641 | E403: =[1]MARURI!CO215 -> 221.11198
A404: 46204 | C404: =[1]OMSPT2!F453 -> 175.77382 | D404: =[1]Cálculos!J405 -> 109.40206 | E404: =[1]MARURI!CO216 -> 223.90955

Sheet otros
A1: Instituto Nacional de Estadística y Geografía (INEGI)
A2: Banco de Información Económica (BIE)
A3: Fecha de consulta: 21/09/2026 12:26:15
A5: Índice base 2018=100
A6: Periodos | B6: Área geográfica | C6: Indicadores económicos de coyuntura > Indicador global de la actividad económica, base 2018 > Series desestacionalizadas y tendencia-ciclo > Total > Serie desestacionalizada > Índice (Índice base 2018=100) Mensual /f2 /p1 | D6: Indicadores económicos de coyuntura > Actividad industrial, base 2018 > Series desestacionalizadas y tendencia-ciclo > Total de la actividad industrial > Serie desestacionalizada > Índice (Índice base 2018=100) Mensual /f1 /p1 | E6: Indicadores económicos de coyuntura > Formación bruta de capital fijo, base 2018 > Series desestacionalizadas y tendencia-ciclo > Por tipo de bien y origen > Total > Serie desestacionalizada > Índice (Índice base 2018=100) Mensual /p1 /f3
A7: 1993/01 p1 | B7: 00 Estados Unidos Mexicanos | C7: 56.277853 | D7: 63.272062 | E7: 54.560765
A8: 1993/02 p1 | B8: 00 Estados Unidos Mexicanos | C8: 57.702215 | D8: 65.754518 | E8: 55.730485
A9: 1993/03 p1 | B9: 00 Estados Unidos Mexicanos | C9: 57.811863 | D9: 66.225466 | E9: 56.495733
A10: 1993/04 p1 | B10: 00 Estados Unidos Mexicanos | C10: 57.183454 | D10: 65.394288 | E10: 56.000916
A11: 1993/05 p1 | B11: 00 Estados Unidos Mexicanos | C11: 57.878169 | D11: 65.388202 | E11: 57.063193
A12: 1993/06 p1 | B12: 00 Estados Unidos Mexicanos | C12: 57.440014 | D12: 64.901136 | E12: 54.901764
A13: 1993/07 p1 | B13: 00 Estados Unidos Mexicanos | C13: 58.309125 | D13: 65.489996 | E13: 55.832937
A14: 1993/08 p1 | B14: 00 Estados Unidos Mexicanos | C14: 58.085725 | D14: 65.646416 | E14: 57.313844
A15: 1993/09 p1 | B15: 00 Estados Unidos Mexicanos | C15: 57.838303 | D15: 65.495639 | E15: 57.925033
A16: 1993/10 p1 | B16: 00 Estados Unidos Mexicanos | C16: 57.752932 | D16: 65.783575 | E16: 59.207872
A17: 1993/11 p1 | B17: 00 Estados Unidos Mexicanos | C17: 57.610755 | D17: 65.820709 | E17: 61.300269
A18: 1993/12 p1 | B18: 00 Estados Unidos Mexicanos | C18: 58.480956 | D18: 66.825409 | E18: 60.962081
... A408: 2026/06 p1 | B408: 00 Estados Unidos Mexicanos | C408: 106.79138 | D408: 102.07733 | E408: 108.73599
A409: 2026/07 p1 | B409: 00 Estados Unidos Mexicanos | D409: 102.53675
A411: Notas y Llamadas:
A412: /p1 Preliminar
A414: Fuente:
A415: /f1 INEGI. Series calculadas por métodos econométricos a partir de las cifras generadas por el Sistema de Cuentas Nacionales de México.
A416: /f2 INEGI. Series calculadas por métodos econométricos a partir de las series originales del Indicador Global de la Actividad Económica.
A417: /f3 INEGI. Series calculadas por métodos econométricos a partir de las series originales del Indicador de la Inversion Fija Bruta.

Sheet Uncertainity
B1: Mexican Policy Uncertainty Index
A2: 35065 | B2: 200.40365
A3: 35096 | B3: 121.81696
A4: 35125 | B4: 174.65147
A5: 35156 | B5: 103.58213
A6: 35186 | B6: 125.61516
A7: 35217 | B7: 94.261245
A8: 35247 | B8: 152.31373
A9: 35278 | B9: 60.99988
A10: 35309 | B10: 116.92176
A11: 35339 | B11: 156.24204
A12: 35370 | B12: 113.20695
A13: 35400 | B13: 148.79132
... A369: 46235 | B369: 82.131248

Sheet desempleo
A1: Instituto Nacional de Estadística y Geografía (INEGI)
A2: Banco de Información Económica (BIE)
A3: Fecha de consulta: 20/08/2026 13:01:41
A4: Porcentaje de la población de 15 años y más|Porcentaje de la Población Económicamente Activa|Porcentaje de la población ocupada|Porcentaje respecto a la PEA
A6: Periodos | B6: Área geográfica | C6: Indicadores económicos de coyuntura > Tasas de ocupación, desocupación y subocupación (resultados mensuales de la ENOE, 15 años y más) > Series desestacionalizadas y tendencia-ciclo > Nacional > Tasa de desocupación > Total > Serie desestacionalizada > Índice (Porcentaje de la Población Económicamente Activa) Mensual /f1
A7: 2005/01 | B7: 00 Estados Unidos Mexicanos | C7: 3.7527354
A8: 2005/02 | B8: 00 Estados Unidos Mexicanos | C8: 3.6012605
A9: 2005/03 | B9: 00 Estados Unidos Mexicanos | C9: 3.6994286
A10: 2005/04 | B10: 00 Estados Unidos Mexicanos | C10: 3.6176324
A11: 2005/05 | B11: 00 Estados Unidos Mexicanos | C11: 3.8376411
A12: 2005/06 | B12: 00 Estados Unidos Mexicanos | C12: 3.834288
A13: 2005/07 | B13: 00 Estados Unidos Mexicanos | C13: 3.6507882
A14: 2005/08 | B14: 00 Estados Unidos Mexicanos | C14: 3.4533949
A15: 2005/09 | B15: 00 Estados Unidos Mexicanos | C15: 3.452324
A16: 2005/10 | B16: 00 Estados Unidos Mexicanos | C16: 3.2424598
A17: 2005/11 | B17: 00 Estados Unidos Mexicanos | C17: 3.0254507
A18: 2005/12 | B18: 00 Estados Unidos Mexicanos | C18: 3.1084049
... A264: 2026/06 | B264: 00 Estados Unidos Mexicanos | C264: 2.8039743
A269: Fuente:
A270: /f1 INEGI. Series calculadas por métodos econométricos a partir de la Encuesta Nacional de Ocupación y Empleo

Sheet IMSS
B1: Empleos
A2: 35612 | B2: 10206251
A3: 35643 | B3: 10291282
A4: 35674 | B4: 10384707
A5: 35704 | B5: 10476716
A6: 35735 | B6: 10563802
A7: 35765 | B7: 10633961
A8: 35796 | B8: 10723592
A9: 35827 | B9: 10778687
A10: 35855 | B10: 10853094
A11: 35886 | B11: 10904591
A12: 35916 | B12: 10939535
A13: 35947 | B13: 10975363
... A350: 46204 | B350: 22646608

Sheet TIIE
A1: Banco de México
A3: Tasas y precios de referencia
A4: TIIE de Fondeo a un día
A6: Fecha de consulta: 21/09/2026 12:20:37
A10: Título | B10: TIIE de Fondeo a Un Día Hábil Bancario, Mediana ponderada por volumen
A11: Periodo disponible | B11: 02/01/2006 - 18/09/2026
A12: Periodicidad | B12: Diaria
A13: Cifra | B13: Tasas Promedio
A14: Unidad | B14: Porcentajes
A15: Base
A16: Aviso
A17: Tipo de información | B17: Niveles
A18: Fecha | B18: SF331451
A19: 38719 | B19: 8.27
A20: 38720 | B20: 8.28
A21: 38721 | B21: 8.28
A22: 38722 | B22: 8.28
A23: 38723 | B23: 8.28
A24: 38726 | B24: 8.28
A25: 38727 | B25: 8.28
A26: 38728 | B26: 8.28
A27: 38729 | B27: 8.28
A28: 38730 | B28: 8.28
A29: 38733 | B29: 8.28
A30: 38734 | B30: 8.27
... A5226: 46283 | B5226: 6.51

Sheet TC
A1: Banco de México
A6: Fecha de consulta: 24/08/2026 12:14:04
A10: Título | B10: Serie histórica del tipo de cambio, Tipo de cambio peso dólar desde 1954
A11: Periodo disponible | B11: May 1954 - Jul 2026
A12: Periodicidad | B12: Mensual
A13: Cifra | B13: Tipo de Cambio
A14: Unidad | B14: Pesos por Dólar
A15: Base
A16: Aviso
A17: Tipo de información | B17: Niveles
A18: Fecha | B18: SF63528
A19: 33604 | B19: 3.06772
A20: 33635 | B20: 3.06291
A21: 33664 | B21: 3.06677
A22: 33695 | B22: 3.06941
A23: 33725 | B23: 3.10184
A24: 33756 | B24: 3.11916
A25: 33786 | B25: 3.11557
A26: 33817 | B26: 3.0881
A27: 33848 | B27: 3.0893
A28: 33878 | B28: 3.12445
A29: 33909 | B29: 3.11832
A30: 33939 | B30: 3.11888
... A433: 46204 | B433: 17.46074

Sheet Balanza
A1: Banco de México
A3: Balanza de pagos
A4: Balanza comercial de mercancías de México, datos desestacionalizados
A6: Fecha de consulta: 21/09/2026 12:23:43
A10: Título | B10: Resumen Datos Desestacionalizados, Exportaciones totales | C10: Resumen Datos Desestacionalizados, Importaciones totales
A11: Periodo disponible | B11: Ene 1993 - Jul 2026 | C11: Ene 1993 - Jul 2026
A12: Periodicidad | B12: Mensual | C12: Mensual
A13: Cifra | B13: Flujos | C13: Flujos
A14: Unidad | B14: Miles de Dólares | C14: Miles de Dólares
A15: Base
A16: Aviso
A17: Tipo de información | B17: Niveles | C17: Niveles
A18: Fecha | B18: SE36664 | C18: SE36672
A19: 33970 | B19: 3902028.9 | C19: 5067290.1
A20: 34001 | B20: 4010668.1 | C20: 5338549.4
A21: 34029 | B21: 4033876.1 | C21: 5297412.8
A22: 34060 | B22: 4204960.8 | C22: 5473612
A23: 34090 | B23: 4158052 | C23: 5433985.3
A24: 34121 | B24: 4423890.8 | C24: 5537211.7
A25: 34151 | B25: 4381213 | C25: 5815561.5
A26: 34182 | B26: 4179254.2 | C26: 5209350.5
A27: 34213 | B27: 4414503.4 | C27: 5541024.4
A28: 34243 | B28: 4781056.3 | C28: 5581937.2
A29: 34274 | B29: 4479535.6 | C29: 5286958.4
A30: 34304 | B30: 4810281.7 | C30: 5722034.4
... A421: 46204 | B421: 77263484 | C421: 76798227
